pytest_suitemanager
